orm/__init__.py
orm/constants.py
orm/exceptions.py
orm/fields.py
orm/models.py
orm/sqlalchemy_fields.py
orm-0.3.1.data/data/LICENSE.md
orm-0.3.1.dist-info/LICENSE.md
orm-0.3.1.dist-info/METADATA
orm-0.3.1.dist-info/WHEEL
orm-0.3.1.dist-info/top_level.txt
orm-0.3.1.dist-info/RECORD
