Metadata-Version: 2.1
Name: orm
Version: 0.3.1
Summary: An async ORM.
Home-page: https://github.com/encode/orm
Author: Tom Christie
Author-email: tom@tomchristie.com
License: BSD
Platform: UNKNOWN
Classifier: Development Status :: 3 - Alpha
Classifier: Environment :: Web Environment
Classifier: Intended Audience :: Developers
Classifier: License :: OSI Approved :: BSD License
Classifier: Operating System :: OS Independent
Classifier: Topic :: Internet :: WWW/HTTP
Classifier: Programming Language :: Python :: 3
Classifier: Programming Language :: Python :: 3.6
Classifier: Programming Language :: Python :: 3.7
Provides-Extra: postgresql
Provides-Extra: mysql
Provides-Extra: sqlite
Provides-Extra: postgresql+aiopg
